GDrivePlayer/__init__.py
GDrivePlayer/anime.py
GDrivePlayer/drama.py
GDrivePlayer/exceptions.py
GDrivePlayer/gdriveplayer.py
GDrivePlayer/movie.py
GDrivePlayer/series.py
GDrivePlayer/utils.py
gdriveplayer-0.2.7.dist-info/LICENSE
gdriveplayer-0.2.7.dist-info/WHEEL
gdriveplayer-0.2.7.dist-info/METADATA
gdriveplayer-0.2.7.dist-info/RECORD
