Metadata-Version: 2.1
Name: gdriveplayer
Version: 0.2.7
Summary: A python wrapper for gdriveplayer.co API
Home-page: https://github.com/adenosinetp10/GDrivePlayerAPI
License: GPL-3.0-or-later
Keywords: poetry,python,api,wrapper,gdrive,gdriveplayer
Author: adenosinetp10
Author-email: adenosinetp10@gmail.com
Requires-Python: >=3.10,<4.0
Classifier: License :: OSI Approved :: GNU General Public License v3 or later (GPLv3+)
Classifier: Programming Language :: Python :: 3
Classifier: Programming Language :: Python :: 3.10
Classifier: Programming Language :: Python :: 3.11
Requires-Dist: requests (>=2.28.1,<3.0.0)
Project-URL: Repository, https://github.com/adenosinetp10/GDrivePlayerAPI
